odoo/addons/purchase_product_usage/README.rst
odoo/addons/purchase_product_usage/__init__.py
odoo/addons/purchase_product_usage/__manifest__.py
odoo/addons/purchase_product_usage/i18n/purchase_product_usage.pot
odoo/addons/purchase_product_usage/i18n/zh_CN.po
odoo/addons/purchase_product_usage/models/__init__.py
odoo/addons/purchase_product_usage/models/account_move.py
odoo/addons/purchase_product_usage/models/purchase_order_line.py
odoo/addons/purchase_product_usage/models/purchase_product_usage.py
odoo/addons/purchase_product_usage/readme/CONFIGURE.rst
odoo/addons/purchase_product_usage/readme/CONTRIBUTORS.rst
odoo/addons/purchase_product_usage/readme/DESCRIPTION.rst
odoo/addons/purchase_product_usage/readme/USAGE.rst
odoo/addons/purchase_product_usage/security/ir.model.access.csv
odoo/addons/purchase_product_usage/security/purchase_product_usage.xml
odoo/addons/purchase_product_usage/static/description/icon.png
odoo/addons/purchase_product_usage/static/description/index.html
odoo/addons/purchase_product_usage/tests/__init__.py
odoo/addons/purchase_product_usage/tests/test_purchase_product_usage.py
odoo/addons/purchase_product_usage/views/purchase_order_line_view.xml
odoo/addons/purchase_product_usage/views/purchase_product_usage_view.xml
odoo13_addon_purchase_product_usage-13.0.1.1.1.dist-info/METADATA
odoo13_addon_purchase_product_usage-13.0.1.1.1.dist-info/WHEEL
odoo13_addon_purchase_product_usage-13.0.1.1.1.dist-info/top_level.txt
odoo13_addon_purchase_product_usage-13.0.1.1.1.dist-info/RECORD
